LICENSE
MANIFEST.in
README.md
setup.cfg
setup.py
django_rest_swagger_django3fix.egg-info/PKG-INFO
django_rest_swagger_django3fix.egg-info/SOURCES.txt
django_rest_swagger_django3fix.egg-info/dependency_links.txt
django_rest_swagger_django3fix.egg-info/not-zip-safe
django_rest_swagger_django3fix.egg-info/requires.txt
django_rest_swagger_django3fix.egg-info/top_level.txt
rest_framework_swagger/__init__.py
rest_framework_swagger/renderers.py
rest_framework_swagger/settings.py
rest_framework_swagger/views.py
rest_framework_swagger/static/rest_framework_swagger/favicon-16x16.png
rest_framework_swagger/static/rest_framework_swagger/favicon-32x32.png
rest_framework_swagger/static/rest_framework_swagger/logo_small.png
rest_framework_swagger/static/rest_framework_swagger/bundles/app.bundle.css
rest_framework_swagger/static/rest_framework_swagger/bundles/app.bundle.js
rest_framework_swagger/static/rest_framework_swagger/bundles/vendors.bundle.css
rest_framework_swagger/static/rest_framework_swagger/bundles/vendors.bundle.js
rest_framework_swagger/templates/rest_framework_swagger/index.html